<?xml version="1.0" encoding="UTF-8"?>
<!DOCTYPE mapper
        PUBLIC "-//mybatis.org//DTD Mapper 3.0//EN"
        "https://mybatis.org/dtd/mybatis-3-mapper.dtd">

<mapper namespace="com.jjang051.petcity.board.dao.BoardDao">

    <!-- 게시판 종류별 목록 조회 + 동물 필터 -->
    <select id="findBoardList"
            resultType="com.jjang051.petcity.board.dto.BoardDto">

        SELECT
        B.BOARD_ID AS boardId,
        B.MEMBER_ID AS memberId,
        B.BOARD_TYPE AS boardType,
        B.TITLE AS title,
        B.CONTENT AS content,
        B.HIT AS hit,
        B.CREATED_AT AS createdAt,
        B.UPDATED_AT AS updatedAt,
        B.ANIMAL_ID AS animalId,

        NVL(M.NICKNAME, '알 수 없음') AS writerNickname,

        AT.ANIMAL_NAME AS animalName,
        PAT.ANIMAL_ID AS parentAnimalId,
        PAT.ANIMAL_NAME AS parentAnimalName,

        (
        SELECT COUNT(*)
        FROM BOARD_COMMENT BC
        WHERE BC.BOARD_ID = B.BOARD_ID
        ) AS commentCount,

        (
        SELECT COUNT(*)
        FROM BOARD_IMAGE BI
        WHERE BI.BOARD_ID = B.BOARD_ID
        ) AS imageCount,

        (
        SELECT IMAGE_URL
        FROM (
        SELECT BI.IMAGE_URL
        FROM BOARD_IMAGE BI
        WHERE BI.BOARD_ID = B.BOARD_ID
        ORDER BY BI.IMAGE_ID ASC
        )
        WHERE ROWNUM = 1
        ) AS thumbnailUrl,

        (
        SELECT LINK_URL
        FROM (
        SELECT BI.LINK_URL
        FROM BOARD_IMAGE BI
        WHERE BI.BOARD_ID = B.BOARD_ID
        ORDER BY BI.IMAGE_ID ASC
        )
        WHERE ROWNUM = 1
        ) AS linkUrl

        FROM BOARD B
        LEFT JOIN APP_MEMBER M
        ON B.MEMBER_ID = M.MEMBER_ID
        LEFT JOIN ANIMAL_TYPE AT
        ON B.ANIMAL_ID = AT.ANIMAL_ID
        LEFT JOIN ANIMAL_TYPE PAT
        ON AT.PARENT_ID = PAT.ANIMAL_ID

        WHERE B.BOARD_TYPE = #{boardType}

        <if test="animalId != null">
            AND B.ANIMAL_ID = #{animalId}
        </if>

        <if test="animalId == null and parentAnimalId != null">
            AND (
            B.ANIMAL_ID = #{parentAnimalId}
            OR B.ANIMAL_ID IN (
            SELECT ANIMAL_ID
            FROM ANIMAL_TYPE
            WHERE PARENT_ID = #{parentAnimalId}
            )
            )
        </if>

        ORDER BY B.BOARD_ID DESC

    </select>


    <!-- 게시글 상세 조회 -->
    <select id="findBoardView"
            resultType="com.jjang051.petcity.board.dto.BoardDto">

        SELECT
        B.BOARD_ID AS boardId,
        B.MEMBER_ID AS memberId,
        B.BOARD_TYPE AS boardType,
        B.TITLE AS title,
        B.CONTENT AS content,
        B.HIT AS hit,
        B.CREATED_AT AS createdAt,
        B.UPDATED_AT AS updatedAt,
        B.ANIMAL_ID AS animalId,

        NVL(M.NICKNAME, '알 수 없음') AS writerNickname,

        AT.ANIMAL_NAME AS animalName,
        PAT.ANIMAL_ID AS parentAnimalId,
        PAT.ANIMAL_NAME AS parentAnimalName,

        (
        SELECT COUNT(*)
        FROM BOARD_COMMENT BC
        WHERE BC.BOARD_ID = B.BOARD_ID
        ) AS commentCount,

        (
        SELECT COUNT(*)
        FROM BOARD_IMAGE BI
        WHERE BI.BOARD_ID = B.BOARD_ID
        ) AS imageCount

        FROM BOARD B
        LEFT JOIN APP_MEMBER M
        ON B.MEMBER_ID = M.MEMBER_ID
        LEFT JOIN ANIMAL_TYPE AT
        ON B.ANIMAL_ID = AT.ANIMAL_ID
        LEFT JOIN ANIMAL_TYPE PAT
        ON AT.PARENT_ID = PAT.ANIMAL_ID

        WHERE B.BOARD_ID = #{boardId}

    </select>


    <!-- 조회수 증가 -->
    <update id="increaseHit">
        UPDATE BOARD
        SET HIT = HIT + 1
        WHERE BOARD_ID = #{boardId}
    </update>


    <!-- 게시글 작성 -->
    <insert id="insertBoard"
            parameterType="com.jjang051.petcity.board.dto.BoardDto">

        <selectKey keyProperty="boardId"
                   resultType="int"
                   order="BEFORE">
            SELECT SEQ_BOARD.NEXTVAL FROM DUAL
        </selectKey>

        INSERT INTO BOARD (
        BOARD_ID,
        MEMBER_ID,
        BOARD_TYPE,
        TITLE,
        CONTENT,
        ANIMAL_ID
        ) VALUES (
        #{boardId},
        #{memberId},
        #{boardType},
        #{title},
        #{content, jdbcType=CLOB},
        #{animalId, jdbcType=NUMERIC}
        )

    </insert>


    <!-- 게시글 이미지 저장 -->
    <insert id="insertBoardImage"
            parameterType="com.jjang051.petcity.board.dto.BoardImageDto">

        INSERT INTO BOARD_IMAGE (
        IMAGE_ID,
        BOARD_ID,
        ORIGINAL_NAME,
        SAVED_NAME,
        IMAGE_URL,
        LINK_URL
        ) VALUES (
        SEQ_BOARD_IMAGE.NEXTVAL,
        #{boardId},
        #{originalName, jdbcType=VARCHAR},
        #{savedName, jdbcType=VARCHAR},
        #{imageUrl, jdbcType=VARCHAR},
        #{linkUrl, jdbcType=VARCHAR}
        )

    </insert>


    <!-- 게시글 이미지 목록 조회 -->
    <select id="findBoardImageList"
            resultType="com.jjang051.petcity.board.dto.BoardImageDto">

        SELECT
        IMAGE_ID AS imageId,
        BOARD_ID AS boardId,
        ORIGINAL_NAME AS originalName,
        SAVED_NAME AS savedName,
        IMAGE_URL AS imageUrl,
        LINK_URL AS linkUrl,
        CREATED_AT AS createdAt
        FROM BOARD_IMAGE
        WHERE BOARD_ID = #{boardId}
        ORDER BY IMAGE_ID ASC

    </select>


    <!-- 동물 대분류 목록 -->
    <select id="findParentAnimalList"
            resultType="com.jjang051.petcity.board.dto.AnimalTypeDto">

        SELECT
        ANIMAL_ID AS animalId,
        ANIMAL_NAME AS animalName,
        CATEGORY AS category,
        PARENT_ID AS parentId
        FROM ANIMAL_TYPE
        WHERE PARENT_ID IS NULL
        ORDER BY ANIMAL_ID ASC

    </select>


    <!-- 대분류에 따른 하위 동물 목록 -->
    <select id="findChildAnimalList"
            resultType="com.jjang051.petcity.board.dto.AnimalTypeDto">

        SELECT
        ANIMAL_ID AS animalId,
        ANIMAL_NAME AS animalName,
        CATEGORY AS category,
        PARENT_ID AS parentId
        FROM ANIMAL_TYPE
        WHERE PARENT_ID = #{parentId}
        ORDER BY ANIMAL_ID ASC

    </select>

    <!-- 게시글 삭제 -->
    <delete id="deleteBoard">
        DELETE FROM BOARD
        WHERE BOARD_ID =#{boardId}
    </delete>

    <!-- 댓글 목록 조회 -->
    <select id="findCommentList"
            resultType="com.jjang051.petcity.board.dto.BoardCommentDto">

        SELECT
        BC.COMMENT_ID AS commentId,
        BC.BOARD_ID AS boardId,
        BC.MEMBER_ID AS memberId,
        BC.CONTENT AS content,
        BC.CREATED_AT AS createdAt,
        BC.UPDATED_AT AS updatedAt,
        NVL(M.NICKNAME, '알 수 없음') AS writerNickname,
        M.ROLE AS writerRole
        FROM BOARD_COMMENT BC
        LEFT JOIN APP_MEMBER M
        ON BC.MEMBER_ID = M.MEMBER_ID
        WHERE BC.BOARD_ID = #{boardId}
        ORDER BY BC.COMMENT_ID ASC

    </select>


    <!-- 댓글 한 개 조회 -->
    <select id="findCommentById"
            resultType="com.jjang051.petcity.board.dto.BoardCommentDto">

        SELECT
        BC.COMMENT_ID AS commentId,
        BC.BOARD_ID AS boardId,
        BC.MEMBER_ID AS memberId,
        BC.CONTENT AS content,
        BC.CREATED_AT AS createdAt,
        BC.UPDATED_AT AS updatedAt,
        NVL(M.NICKNAME, '알 수 없음') AS writerNickname,
        M.ROLE AS writerRole
        FROM BOARD_COMMENT BC
        LEFT JOIN APP_MEMBER M
        ON BC.MEMBER_ID = M.MEMBER_ID
        WHERE BC.COMMENT_ID = #{commentId}

    </select>


    <!-- 댓글 등록 -->
    <insert id="insertComment"
            parameterType="com.jjang051.petcity.board.dto.BoardCommentDto">

        INSERT INTO BOARD_COMMENT (
        COMMENT_ID,
        BOARD_ID,
        MEMBER_ID,
        CONTENT
        ) VALUES (
        SEQ_BOARD_COMMENT.NEXTVAL,
        #{boardId},
        #{memberId},
        #{content}
        )

    </insert>


    <!-- 댓글 삭제 -->
    <delete id="deleteComment">

        DELETE FROM BOARD_COMMENT
        WHERE COMMENT_ID = #{commentId}

    </delete>


    <!-- 로그인 아이디로 회원 번호 조회 -->
    <select id="findMemberIdByLoginId"
            resultType="int">

        SELECT MEMBER_ID
        FROM APP_MEMBER
        WHERE LOGIN_ID = #{loginId}

    </select>

    <!-- 댓글 수정-->
    <update id="updateComment">

        UPDATE BOARD_COMMENT
        SET CONTENT =#{content},
         UPDATED_AT = SYSTIMESTAMP
        WHERE COMMENT_ID = #{commentId}
    </update>

    <!--게시글 수정-->
    <update id="updateBoard"
            parameterType="com.jjang051.petcity.board.dto.BoardDto">

        UPDATE BOARD
        SET TITLE = #{title},
          CONTENT = #{content, jdbcType =CLOB},
          ANIMAL_ID = #{animalId, jdbcType=NUMERIC},
          UPDATED_AT = SYSTIMESTAMP
        WHERE BOARD_ID = #{boardId}
    </update>
    <!--게시글 대표 이미지 db 정보 삭제-->
    <delete id="deleteBoardImages">

        DELETE FROM BOARD_IMAGE
        WHERE BOARD_ID = #{boardId}
    </delete>

    <!--기존 멍냥백서 대표 이미지 링크 수정-->
    <update id ="updateBoardImageLink">

        UPDATE BOARD_IMAGE
        SET LINK_URL = #{linkUrl, jdbcType=VARCHAR}
        WHERE BOARD_ID = #{boardId}

    </update>




</mapper>